LICENSE
MANIFEST.in
README.markdown
setup.py
tests.py
bertrpc/__init__.py
bertrpc/client.py
bertrpc/error.py
insight_bertrpc.egg-info/PKG-INFO
insight_bertrpc.egg-info/SOURCES.txt
insight_bertrpc.egg-info/dependency_links.txt
insight_bertrpc.egg-info/requires.txt
insight_bertrpc.egg-info/top_level.txt