Metadata-Version: 1.0
Name: insight-bertrpc
Version: 0.1.2
Summary: BERT-RPC Library
Home-page: https://github.com/teaminsight/python-bertrpc
Author: Team Insight
Author-email: jordan.bach@reelfx.com
License: MIT
Platform: UNKNOWN
Classifier: Intended Audience :: Developers
Classifier: Operating System :: OS Independent
Classifier: Programming Language :: Python
Classifier: Topic :: Software Development :: Libraries :: Python Modules
